gym_super_mario_bros/__init__.py
gym_super_mario_bros/_registration.py
gym_super_mario_bros/actions.py
gym_super_mario_bros/smb_env.py
gym_super_mario_bros/smb_random_stages_env.py
gym_super_mario_bros/_app/__init__.py
gym_super_mario_bros/_app/cli.py
gym_super_mario_bros/_roms/__init__.py
gym_super_mario_bros/_roms/decode_target.py
gym_super_mario_bros/_roms/rom_path.py
gym_super_mario_bros/_roms/super-mario-bros-2-downsample.nes
gym_super_mario_bros/_roms/super-mario-bros-2.nes
gym_super_mario_bros/_roms/super-mario-bros-downsample.nes
gym_super_mario_bros/_roms/super-mario-bros-pixel.nes
gym_super_mario_bros/_roms/super-mario-bros-rectangle.nes
gym_super_mario_bros/_roms/super-mario-bros.nes
gym_super_mario_bros-7.4.0.dist-info/LICENSE
gym_super_mario_bros-7.4.0.dist-info/METADATA
gym_super_mario_bros-7.4.0.dist-info/WHEEL
gym_super_mario_bros-7.4.0.dist-info/entry_points.txt
gym_super_mario_bros-7.4.0.dist-info/top_level.txt
gym_super_mario_bros-7.4.0.dist-info/RECORD
