Metadata-Version: 2.1
Name: gym-super-mario-bros
Version: 7.4.0
Summary: Super Mario Bros. for OpenAI Gym
Home-page: https://github.com/Kautenja/gym-super-mario-bros
Author: Christian Kauten
Author-email: kautencreations@gmail.com
License: Proprietary
Keywords: OpenAI-Gym NES Super-Mario-Bros Lost-Levels Reinforcement-Learning-Environment
Platform: UNKNOWN
Classifier: Development Status :: 5 - Production/Stable
Classifier: Intended Audience :: Developers
Classifier: Intended Audience :: Science/Research
Classifier: License :: Free For Educational Use
Classifier: Operating System :: MacOS :: MacOS X
Classifier: Operating System :: POSIX :: Linux
Classifier: Operating System :: Microsoft :: Windows
Classifier: Programming Language :: Python :: 3 :: Only
Classifier: Programming Language :: Python :: 3.5
Classifier: Programming Language :: Python :: 3.6
Classifier: Programming Language :: Python :: 3.7
Classifier: Programming Language :: Python :: 3.8
Classifier: Topic :: Games/Entertainment :: Side-Scrolling/Arcade Games
Classifier: Topic :: Scientific/Engineering :: Artificial Intelligence
